{
    "location": "https://www.google.com.ar/maps/place/Buenos+Aires,+Cdad.+Aut%C3%B3noma+de+Buenos+Aires/@-34.6156548,-58.5156999,12z/data=!3m1!4b1!4m6!3m5!1s0x95bcca3b4ef90cbd:0xa0b3812e88e88e87!8m2!3d-34.6036739!4d-58.3821215!16zL20vMDFseTVt?hl=es&entry=ttu&g_ep=EgoyMDI1MDQwOC4wIKXMDSoASAFQAw%3D%3D",
    "email": "mailto:sofialvarezrodero@gmail.com",
    "whatsapp": "https://wa.link/vkscmu",
    "github": "https://github.com/Sofii2301",
    "linkedIn": "https://www.linkedin.com/in/sofi-alvarez-rodero",
    "address": "https://www.google.com.ar/maps/place/Av.+La+Plata+61,+C1184+Cdad.+Aut%C3%B3noma+de+Buenos+Aires/@-34.6159384,-58.4318322,17z/data=!3m1!4b1!4m6!3m5!1s0x95bcca4356c3d27b:0x5d16addf8e6ba1e3!8m2!3d-34.6159428!4d-58.4292573!16s%2Fg%2F11fwf59l9v?hl=es&entry=ttu&g_ep=EgoyMDI1MDQwOC4wIKXMDSoASAFQAw%3D%3D",
    "high_school_certificte": "https://drive.google.com/file/d/1EkfEUQ4Agw-17pQ4cvSnIg4zgF9bxPzp/view",
    "title_in_process_certificate": "https://docs.google.com/document/d/1000kv7z1vSJ18HaeesvZNa6kTtimWu5UVA2Lxcv9z7g/edit?usp=sharing",
    "argentina_programa_certificate": "https://mumuki.io/argentina-programa/certificates/verify/a4WZO6r-gCnwvcG6",
    "scrum_certificate": "https://c46e136a583f7e334124-ac22991740ab4ff17e21daf2ed577041.ssl.cf1.rackcdn.com/Certificate/ScrumFundamentalsCertified-SofiaAlvarezRodero-1020990.pdf"
}